{
  "dist/index.d.ts": {
    "size": "1.46KB",
    "brotli": "412B",
    "gzip": "510B"
  },
  "dist/index.js": {
    "size": "8.285KB",
    "brotli": "2.138KB",
    "gzip": "2.426KB"
  },
  "dist/index.js.map": {
    "size": "8.731KB",
    "brotli": "1.401KB",
    "gzip": "1.528KB"
  },
  "dist/index.min.js": {
    "size": "3.103KB",
    "brotli": "1.33KB",
    "gzip": "1.494KB"
  },
  "dist/lib/utils.d.ts": {
    "size": "59B",
    "brotli": "55B",
    "gzip": "72B"
  },
  "dist/lib/utils.js": {
    "size": "530B",
    "brotli": "235B",
    "gzip": "297B"
  },
  "dist/lib/utils.js.map": {
    "size": "579B",
    "brotli": "229B",
    "gzip": "258B"
  },
  "esm/index.d.ts": {
    "size": "1.46KB",
    "brotli": "412B",
    "gzip": "510B"
  },
  "esm/index.js": {
    "size": "7.708KB",
    "brotli": "1.998KB",
    "gzip": "2.262KB"
  },
  "esm/index.js.map": {
    "size": "8.651KB",
    "brotli": "1.356KB",
    "gzip": "1.464KB"
  },
  "esm/index.min.js": {
    "size": "2.513KB",
    "brotli": "1.107KB",
    "gzip": "1.244KB"
  },
  "esm/lib/utils.d.ts": {
    "size": "59B",
    "brotli": "55B",
    "gzip": "72B"
  },
  "esm/lib/utils.js": {
    "size": "392B",
    "brotli": "179B",
    "gzip": "229B"
  },
  "esm/lib/utils.js.map": {
    "size": "569B",
    "brotli": "222B",
    "gzip": "250B"
  }
}